monpro/sv/monpro.sv
`timescale 1ns / 1ps

typedef enum logic [2:0] {
    MONPRO_IDLE,
    MONPRO_LOAD,
    MONPRO_CASE1A,
    MONPRO_CASE1B,
    MONPRO_CASE2,
    MONPRO_CASE3,
    MONPRO_CASE4,
    MONPRO_DONE
} monpro_state_t;

module monpro #(
    parameter unsigned DATAWIDTH = 64
    ) (
    input logic clk,
    input logic rstn,

    input logic start,
    output logic ready,
    output logic o_valid,

    input logic unsigned [DATAWIDTH-1:0] i_A,
    input logic unsigned [DATAWIDTH-1:0] i_B,
    input logic unsigned [DATAWIDTH-1:0] i_N,
    output logic unsigned [DATAWIDTH-1:0] o_U
    );

    // Iteration counter
    logic unsigned [$clog2(DATAWIDTH):0] i_cnt;

    // Data registers
    logic unsigned [DATAWIDTH-1:0] r_A;
    logic unsigned [DATAWIDTH-1:0] r_B;
    logic unsigned [DATAWIDTH-1:0] r_N;

    logic unsigned [DATAWIDTH:0] U_reg;

    // Combinational
    logic unsigned [DATAWIDTH:0] adder_input;
    logic unsigned [DATAWIDTH:0] adder_result;
    logic unsigned [DATAWIDTH:0] adder_bypass_result;
    logic unsigned [DATAWIDTH:0] monpro_comb_result;

    logic adder_input_mux_select, adder_bypass_mux_select, adder_result_shift_mux_select;

    always_comb begin
        case (current_state)

            default: begin
                // mux select signals will be latched
            end
        endcase

        // Select adder input
        if (adder_input_mux_select) begin
            adder_input = {1'b0, r_N};
        end else begin
            adder_input = {1'b0, r_B};
        end

        adder_result = U_reg + adder_input;

        if (adder_bypass_mux_select) begin
            adder_bypass_result = U_reg;
        end else begin
            adder_bypass_result = adder_result;
        end

        if (adder_result_shift_mux_select) begin
            monpro_comb_result = adder_bypass_result;
        end else begin
            monpro_comb_result = adder_bypass_result >> 1;
        end
    end

    // State
    monpro_state_t current_state = MONPRO_IDLE, next_state = MONPRO_IDLE;
    always_ff @(posedge clk) begin
        if (~rstn) begin
            current_state <= MONPRO_IDLE;
        end else begin
            current_state <= next_state;
        end
    end

    always_comb begin
        next_state = current_state;
        ready = 0;

        case (current_state)
            MONPRO_IDLE: begin
                if (start) begin
                    next_state = MONPRO_LOAD;
                end else begin
                    ready = 1;
                end
            end

            MONPRO_LOAD: begin
                if (i_cnt == DATAWIDTH) begin
                    next_state = MONPRO_DONE;
                end else begin
                    if (r_A[0] && U_reg[0]) begin
                        next_state = MONPRO_CASE1A;
                    end else if (r_A[0] && ~U_reg[0]) begin
                        next_state = MONPRO_CASE2;
                    end else if (~r_A[0] && U_reg[0]) begin
                        next_state = MONPRO_CASE3;
                    end else begin
                        next_state = MONPRO_CASE4;
                    end
                end
            end

            MONPRO_CASE1A: begin
                next_state = MONPRO_CASE1B;
            end

            MONPRO_CASE1B: begin
                next_state = MONPRO_LOAD;
            end

            MONPRO_CASE2: begin
                next_state = MONPRO_LOAD;
            end

            MONPRO_CASE3: begin
                next_state = MONPRO_LOAD;
            end

            MONPRO_CASE4: begin
                next_state = MONPRO_LOAD;
            end

            MONPRO_DONE: begin
                next_state = MONPRO_IDLE;
            end

            default: begin
                next_state = MONPRO_IDLE;
            end
        endcase
    end

    // Register results
    always_ff @(posedge clk) begin
        if (~rstn) begin
            i_cnt <= '0;

            r_A <= '0;
            r_B <= '0;
            r_N <= '0;
            U_reg <= '0;

            // Reset output data
            o_U <= '0;
            o_valid <= '0;
        end else begin
            case (current_state)
                MONPRO_IDLE: begin
                    if (start) begin
                        r_A <= i_A;
                        r_B <= i_B;
                        r_N <= i_N;
                        U_reg <= '0;
                    end
                    i_cnt <= '0;

                    // Reset output data
                    o_U <= '0;
                    o_valid <= '0;
                    // U_reg <= monpro_comb_result;
                end

                MONPRO_LOAD: begin
                    if (r_A[0] && U_reg[0]) begin
                        adder_input_mux_select <= 0;
                        adder_bypass_mux_select <= 0;
                        adder_result_shift_mux_select <= 1;
                    end else if (r_A[0] && ~U_reg[0]) begin
                        adder_input_mux_select <= 0;
                        adder_bypass_mux_select <= 0;
                        adder_result_shift_mux_select <= 0;
                    end else if (~r_A[0] && U_reg[0]) begin
                        adder_input_mux_select <= 1;
                        adder_bypass_mux_select <= 0;
                        adder_result_shift_mux_select <= 0;
                    end else begin
                        adder_input_mux_select <= 1;
                        adder_bypass_mux_select <= 1;
                        adder_result_shift_mux_select <= 0;
                    end
                    i_cnt <= i_cnt + 1;
                    r_A <= {1'b0, r_A[DATAWIDTH-1:1]};
                end

                MONPRO_CASE1A: begin
                    U_reg <= monpro_comb_result;
                    adder_input_mux_select <= 1;
                    adder_bypass_mux_select <= 0;
                    adder_result_shift_mux_select <= 0;
                end

                MONPRO_CASE1B: begin
                    U_reg <= monpro_comb_result;
                end

                MONPRO_CASE2: begin
                    U_reg <= monpro_comb_result;
                end

                MONPRO_CASE3: begin
                    U_reg <= monpro_comb_result;
                end

                MONPRO_CASE4: begin
                    U_reg <= monpro_comb_result;
                end

                MONPRO_DONE: begin
                    o_U <= U_reg[DATAWIDTH-1:0];
                    o_valid <= '1;
                end

                default: begin
                    o_U <= '0;
                    o_valid <= '0;
                end
            endcase
        end
    end

endmodule

monpro/sv/waveform.vcd
$version Generated by VerilatedVcd $end
$date Thu Oct 31 17:01:46 2024
 $end
$timescale   1ps $end

 $scope module TOP $end
  $var wire  1 = clk $end
  $var wire 64 B i_A [63:0] $end
  $var wire 64 D i_B [63:0] $end
  $var wire 64 F i_N [63:0] $end
  $var wire 64 H o_U [63:0] $end
  $var wire  1 A o_valid $end
  $var wire  1 @ ready $end
  $var wire  1 > rstn $end
  $var wire  1 ? start $end
  $scope module monpro $end
   $var wire 32 K DATAWIDTH [31:0] $end
   $var wire 65 * U_reg [64:0] $end
   $var wire  1 : adder_bypass_mux_select $end
   $var wire 65 3 adder_bypass_result [64:0] $end
   $var wire 65 - adder_input [64:0] $end
   $var wire  1 9 adder_input_mux_select $end
   $var wire 65 0 adder_result [64:0] $end
   $var wire  1 ; adder_result_shift_mux_select $end
   $var wire  1 = clk $end
   $var wire  3 < current_state [2:0] $end
   $var wire 64 B i_A [63:0] $end
   $var wire 64 D i_B [63:0] $end
   $var wire 64 F i_N [63:0] $end
   $var wire  7 # i_cnt [6:0] $end
   $var wire 65 6 monpro_comb_result [64:0] $end
   $var wire  3 J next_state [2:0] $end
   $var wire 64 H o_U [63:0] $end
   $var wire  1 A o_valid $end
   $var wire 64 $ r_A [63:0] $end
   $var wire 64 & r_B [63:0] $end
   $var wire 64 ( r_N [63:0] $end
   $var wire  1 @ ready $end
   $var wire  1 > rstn $end
   $var wire  1 ? start $end
  $upscope $end
 $upscope $end
$enddefinitions $end


#0
b0111000 #
b0011110010110100111101000011010000111001111010011111010011101001 $
b1001001100100010100110101000001100110101011110011110001111000110 &
b0000000010001110000011001111100010010100010111111111111000100101 (
b11011000111110011111110100101111100101101101001001100010000001111 *
b00000000010001110000011001111100010010100010111111111111000100101 -
b11011001010000010000001110101011111000010000001001100001000110100 0
b11011000111110011111110100101111100101101101001001100010000001111 3
b01101100011111001111111010010111110010110110100100110001000000111 6
19
1:
0;
b000 <
0=
0>
0?
1@
1A
b0000000000000000000000000000000000000000000000000000000000000000 B
b0000000000000000000000000000000000000000000000000000000000000000 D
b0000000000000000000000000000000000000000000000000000000000000000 F
b1000101100010110110101110001001110000000100110101000010000011001 H
b000 J
b00000000000000000000000001000000 K
#1
b0000000 #
b0000000000000000000000000000000000000000000000000000000000000000 $
b0000000000000000000000000000000000000000000000000000000000000000 &
b0000000000000000000000000000000000000000000000000000000000000000 (
b00000000000000000000000000000000000000000000000000000000000000000 *
b00000000000000000000000000000000000000000000000000000000000000000 -
b00000000000000000000000000000000000000000000000000000000000000000 0
b00000000000000000000000000000000000000000000000000000000000000000 3
b00000000000000000000000000000000000000000000000000000000000000000 6
1=
0A
b0000000000000000000000000000000000000000000000000000000000000000 H
#2
0=
#3
1=
#4
0=
#5
1=
#6
0=
#7
1=
#8
0=
1>
#9
1=
#10
0=
#11
1=
#12
0=
#13
1=
#14
0=
#15
1=
#16
0=
#17
1=
#18
0=
#19
1=
#20
0=
#21
1=
#22
0=
#23
1=
1?
b0010001010001100000011100101011111101010101000011010111101110000 B
b0010001010001100000011100101011111101010101000011010111101110000 D
b0011010101100111110010101110011101010111101111011000000000011111 F
#24
0=
0@
b001 J
#25
b0010001010001100000011100101011111101010101000011010111101110000 $
b0010001010001100000011100101011111101010101000011010111101110000 &
b0011010101100111110010101110011101010111101111011000000000011111 (
b00011010101100111110010101110011101010111101111011000000000011111 -
b00011010101100111110010101110011101010111101111011000000000011111 0
b001 <
1=
0?
b0000000000000000000000000000000000000000000000000000000000000000 B
b0000000000000000000000000000000000000000000000000000000000000000 D
b0000000000000000000000000000000000000000000000000000000000000000 F
b110 J
#26
0=
#27
b0000001 #
b0001000101000110000001110010101111110101010100001101011110111000 $
b110 <
1=
b001 J
#28
0=
#29
b001 <
1=
b110 J
#30
0=
#31
b0000010 #
b0000100010100011000000111001010111111010101010000110101111011100 $
b110 <
1=
b001 J
#32
0=
#33
b001 <
1=
b110 J
#34
0=
#35
b0000011 #
b0000010001010001100000011100101011111101010101000011010111101110 $
b110 <
1=
b001 J
#36
0=
#37
b001 <
1=
b110 J
#38
0=
#39
b0000100 #
b0000001000101000110000001110010101111110101010100001101011110111 $
b110 <
1=
b001 J
#40
0=
#41
b001 <
1=
b100 J
#42
0=
#43
b0000101 #
b0000000100010100011000000111001010111111010101010000110101111011 $
b00010001010001100000011100101011111101010101000011010111101110000 -
b00010001010001100000011100101011111101010101000011010111101110000 0
b00010001010001100000011100101011111101010101000011010111101110000 3
b00001000101000110000001110010101111110101010100001101011110111000 6
09
0:
b100 <
1=
b001 J
#44
0=
#45
b00001000101000110000001110010101111110101010100001101011110111000 *
b00011001111010010000101011000001111011111111100101000011100101000 0
b00011001111010010000101011000001111011111111100101000011100101000 3
b00001100111101001000010101100000111101111111110010100001110010100 6
b001 <
1=
b100 J
#46
0=
#47
b0000110 #
b0000000010001010001100000011100101011111101010101000011010111101 $
b100 <
1=
b001 J
#48
0=
#49
b00001100111101001000010101100000111101111111110010100001110010100 *
b00011110001110101000110010001100111011010100110101111001100000100 0
b00011110001110101000110010001100111011010100110101111001100000100 3
b00001111000111010100011001000110011101101010011010111100110000010 6
b001 <
1=
b100 J
#50
0=
#51
b0000111 #
b0000000001000101000110000001110010101111110101010100001101011110 $
b100 <
1=
b001 J
#52
0=
#53
b00001111000111010100011001000110011101101010011010111100110000010 *
b00100000011000110100110101110010011010111111011110010100011110010 0
b00100000011000110100110101110010011010111111011110010100011110010 3
b00010000001100011010011010111001001101011111101111001010001111001 6
b001 <
1=
b110 J
#54
0=
#55
b0001000 #
b0000000000100010100011000000111001010111111010101010000110101111 $
b00011010101100111110010101110011101010111101111011000000000011111 -
b00101001110100010010101110111010001000101000010101111100110100001 0
b00001111000111010100011001000110011101101010011010111100110000010 3
b00000111100011101010001100100011001110110101001101011110011000001 6
19
1:
b110 <
1=
b001 J
#56
0=
#57
b00000111100011101010001100100011001110110101001101011110011000001 *
b00100010010000101000100010010110111001110011001000011110011100000 0
b00000111100011101010001100100011001110110101001101011110011000001 3
b00000011110001110101000110010001100111011010100110101111001100000 6
b001 <
1=
b010 J
#58
0=
#59
b0001001 #
b0000000000010001010001100000011100101011111101010101000011010111 $
b00010001010001100000011100101011111101010101000011010111101110000 -
b00011000110101001010101001001111001100001010010000110110000110001 0
b00011000110101001010101001001111001100001010010000110110000110001 3
b00011000110101001010101001001111001100001010010000110110000110001 6
09
0:
1;
b010 <
1=
b011 J
#60
0=
#61
b00011000110101001010101001001111001100001010010000110110000110001 *
b00011010101100111110010101110011101010111101111011000000000011111 -
b00110011100010001000111111000010110111001000001011110110001010000 0
b00110011100010001000111111000010110111001000001011110110001010000 3
b00011001110001000100011111100001011011100100000101111011000101000 6
19
0;
b011 <
1=
b001 J
#62
0=
#63
b00011001110001000100011111100001011011100100000101111011000101000 *
b00110100011110000010110101010101000110100010000000111011001000111 0
b00110100011110000010110101010101000110100010000000111011001000111 3
b00011010001111000001011010101010100011010001000000011101100100011 6
b001 <
1=
b100 J
#64
0=
#65
b0001010 #
b0000000000001000101000110000001110010101111110101010100001101011 $
b00010001010001100000011100101011111101010101000011010111101110000 -
b00101011000010100100111100001101011000111001001001010010110011000 0
b00101011000010100100111100001101011000111001001001010010110011000 3
b00010101100001010010011110000110101100011100100100101001011001100 6
09
b100 <
1=
b001 J
#66
0=
#67
b00010101100001010010011110000110101100011100100100101001011001100 *
b00100110110010110010111010110010101001110001101000000001000111100 0
b00100110110010110010111010110010101001110001101000000001000111100 3
b00010011011001011001011101011001010100111000110100000000100011110 6
b001 <
1=
b100 J
#68
0=
#69
b0001011 #
b0000000000000100010100011000000111001010111111010101010000110101 $
b100 <
1=
b001 J
#70
0=
#71
b00010011011001011001011101011001010100111000110100000000100011110 *
b00100100101010111001111010000101010010001101110111011000010001110 0
b00100100101010111001111010000101010010001101110111011000010001110 3
b00010010010101011100111101000010101001000110111011101100001000111 6
b001 <
1=
b100 J
#72
0=
#73
b0001100 #
b0000000000000010001010001100000011100101011111101010101000011010 $
b100 <
1=
b001 J
#74
0=
#75
b00010010010101011100111101000010101001000110111011101100001000111 *
b00100011100110111101011001101110100110011011111111000011110110111 0
b00100011100110111101011001101110100110011011111111000011110110111 3
b00010001110011011110101100110111010011001101111111100001111011011 6
b001 <
1=
b101 J
#76
0=
#77
b0001101 #
b0000000000000001000101000110000001110010101111110101010100001101 $
b00011010101100111110010101110011101010111101111011000000000011111 -
b00101101000010011011010010110110010100000100110110101100001100110 0
b00101101000010011011010010110110010100000100110110101100001100110 3
b00010110100001001101101001011011001010000010011011010110000110011 6
19
b101 <
1=
b001 J
#78
0=
#79
b00010110100001001101101001011011001010000010011011010110000110011 *
b00110001001110001011111111001110110101000000010110010110001010010 0
b00110001001110001011111111001110110101000000010110010110001010010 3
b00011000100111000101111111100111011010100000001011001011000101001 6
b001 <
1=
b010 J
#80
0=
#81
b0001110 #
b0000000000000000100010100011000000111001010111111010101010000110 $
b00010001010001100000011100101011111101010101000011010111101110000 -
b00100111110010101110000110000111000111010111011110101101110100011 0
b00100111110010101110000110000111000111010111011110101101110100011 3
b00100111110010101110000110000111000111010111011110101101110100011 6
09
1;
b010 <
1=
b011 J
#82
0=
#83
b00100111110010101110000110000111000111010111011110101101110100011 *
b00011010101100111110010101110011101010111101111011000000000011111 -
b01000010011111101100011011111010110010010101011001101101111000010 0
b01000010011111101100011011111010110010010101011001101101111000010 3
b00100001001111110110001101111101011001001010101100110110111100001 6
19
0;
b011 <
1=
b001 J
#84
0=
#85
b00100001001111110110001101111101011001001010101100110110111100001 *
b00111011111100110100100011110001000100001000100111110111000000000 0
b00111011111100110100100011110001000100001000100111110111000000000 3
b00011101111110011010010001111000100010000100010011111011100000000 6
b001 <
1=
b101 J
#86
0=
#87
b0001111 #
b0000000000000000010001010001100000011100101011111101010101000011 $
b101 <
1=
b001 J
#88
0=
#89
b00011101111110011010010001111000100010000100010011111011100000000 *
b00111000101011011000100111101100001101000010001110111011100011111 0
b00111000101011011000100111101100001101000010001110111011100011111 3
b00011100010101101100010011110110000110100001000111011101110001111 6
b001 <
1=
b100 J
#90
0=
#91
b0010000 #
b0000000000000000001000101000110000001110010101111110101010100001 $
b00010001010001100000011100101011111101010101000011010111101110000 -
b00101111001111111010101110100100011111011001010111010011001110000 0
b00101111001111111010101110100100011111011001010111010011001110000 3
b00010111100111111101010111010010001111101100101011101001100111000 6
09
b100 <
1=
b001 J
#92
0=
#93
b00010111100111111101010111010010001111101100101011101001100111000 *
b00101000111001011101110011111110001101000001101111000001010101000 0
b00101000111001011101110011111110001101000001101111000001010101000 3
b00010100011100101110111001111111000110100000110111100000101010100 6
b001 <
1=
b100 J
#94
0=
#95
b0010001 #
b0000000000000000000100010100011000000111001010111111010101010000 $
b100 <
1=
b001 J
#96
0=
#97
b00010100011100101110111001111111000110100000110111100000101010100 *
b00100101101110001111010110101011000011110101111010111000011000100 0
b00100101101110001111010110101011000011110101111010111000011000100 3
b00010010110111000111101011010101100001111010111101011100001100010 6
b001 <
1=
b110 J
#98
0=
#99
b0010010 #
b0000000000000000000010001010001100000011100101011111101010101000 $
b00011010101100111110010101110011101010111101111011000000000011111 -
b00101111001001101101001111110010110001011110110010100000101110011 0
b00010100011100101110111001111111000110100000110111100000101010100 3
b00001010001110010111011100111111100011010000011011110000010101010 6
19
1:
b110 <
1=
b001 J
#100
0=
#101
b00001010001110010111011100111111100011010000011011110000010101010 *
b00100100111011010101110010110011001110001110010110110000011001001 0
b00001010001110010111011100111111100011010000011011110000010101010 3
b00000101000111001011101110011111110001101000001101111000001010101 6
b001 <
1=
b110 J
#102
0=
#103
b0010011 #
b0000000000000000000001000101000110000001110010101111110101010100 $
b110 <
1=
b001 J
#104
0=
#105
b00000101000111001011101110011111110001101000001101111000001010101 *
b00011111110100001010000100010011011100100110001000111000001110100 0
b00000101000111001011101110011111110001101000001101111000001010101 3
b00000010100011100101110111001111111000110100000110111100000101010 6
b001 <
1=
b101 J
#106
0=
#107
b0010100 #
b0000000000000000000000100010100011000000111001010111111010101010 $
b00011111110100001010000100010011011100100110001000111000001110100 3
b00001111111010000101000010001001101110010011000100011100000111010 6
0:
b101 <
1=
b001 J
#108
0=
#109
b00001111111010000101000010001001101110010011000100011100000111010 *
b00101010100111000011010111111101011001010000111111011100001011001 0
b00101010100111000011010111111101011001010000111111011100001011001 3
b00010101010011100001101011111110101100101000011111101110000101100 6
b001 <
1=
b110 J
#110
0=
#111
b0010101 #
b0000000000000000000000010001010001100000011100101011111101010101 $
b00001111111010000101000010001001101110010011000100011100000111010 3
b00000111111101000010100001000100110111001001100010001110000011101 6
1:
b110 <
1=
b001 J
#112
0=
#113
b00000111111101000010100001000100110111001001100010001110000011101 *
b00100010101010000000110110111000100010000111011101001110000111100 0
b00000111111101000010100001000100110111001001100010001110000011101 3
b00000011111110100001010000100010011011100100110001000111000001110 6
b001 <
1=
b010 J
#114
0=
#115
b0010110 #
b0000000000000000000000001000101000110000001110010101111110101010 $
b00010001010001100000011100101011111101010101000011010111101110000 -
b00011001001110100010111101110000110100011110100101100101110001101 0
b00011001001110100010111101110000110100011110100101100101110001101 3
b00011001001110100010111101110000110100011110100101100101110001101 6
09
0:
1;
b010 <
1=
b011 J
#116
0=
#117
b00011001001110100010111101110000110100011110100101100101110001101 *
b00011010101100111110010101110011101010111101111011000000000011111 -
b00110011111011100001010011100100011111011100100000100101110101100 0
b00110011111011100001010011100100011111011100100000100101110101100 3
b00011001111101110000101001110010001111101110010000010010111010110 6
19
0;
b011 <
1=
b001 J
#118
0=
#119
b00011001111101110000101001110010001111101110010000010010111010110 *
b00110100101010101110111111100101111010101100001011010010111110101 0
b00110100101010101110111111100101111010101100001011010010111110101 3
b00011010010101010111011111110010111101010110000101101001011111010 6
b001 <
1=
b110 J
#120
0=
#121
b0010111 #
b0000000000000000000000000100010100011000000111001010111111010101 $
b00011001111101110000101001110010001111101110010000010010111010110 3
b00001100111110111000010100111001000111110111001000001001011101011 6
1:
b110 <
1=
b001 J
#122
0=
#123
b00001100111110111000010100111001000111110111001000001001011101011 *
b00100111101011110110101010101100110010110101000011001001100001010 0
b00001100111110111000010100111001000111110111001000001001011101011 3
b00000110011111011100001010011100100011111011100100000100101110101 6
b001 <
1=
b010 J
#124
0=
#125
b0011000 #
b0000000000000000000000000010001010001100000011100101011111101010 $
b00010001010001100000011100101011111101010101000011010111101110000 -
b00011110010000011000110001100101000101001100001011100001001011011 0
b00011110010000011000110001100101000101001100001011100001001011011 3
b00011110010000011000110001100101000101001100001011100001001011011 6
09
0:
1;
b010 <
1=
b011 J
#126
0=
#127
b00011110010000011000110001100101000101001100001011100001001011011 *
b00011010101100111110010101110011101010111101111011000000000011111 -
b00111000111101010111000111011000110000001010000110100001001111010 0
b00111000111101010111000111011000110000001010000110100001001111010 3
b00011100011110101011100011101100011000000101000011010000100111101 6
19
0;
b011 <
1=
b001 J
#128
0=
#129
b00011100011110101011100011101100011000000101000011010000100111101 *
b00110111001011101001111001100000000011000010111110010000101011100 0
b00110111001011101001111001100000000011000010111110010000101011100 3
b00011011100101110100111100110000000001100001011111001000010101110 6
b001 <
1=
b101 J
#130
0=
#131
b0011001 #
b0000000000000000000000000001000101000110000001110010101111110101 $
b101 <
1=
b001 J
#132
0=
#133
b00011011100101110100111100110000000001100001011111001000010101110 *
b00110110010010110011010010100011101100011111011010001000011001101 0
b00110110010010110011010010100011101100011111011010001000011001101 3
b00011011001001011001101001010001110110001111101101000100001100110 6
b001 <
1=
b100 J
#134
0=
#135
b0011010 #
b0000000000000000000000000000100010100011000000111001010111111010 $
b00010001010001100000011100101011111101010101000011010111101110000 -
b00101100110111010101011001011011111110110110100010100000000011110 0
b00101100110111010101011001011011111110110110100010100000000011110 3
b00010110011011101010101100101101111111011011010001010000000001111 6
09
b100 <
1=
b001 J
#136
0=
#137
b00010110011011101010101100101101111111011011010001010000000001111 *
b00100111101101001011001001011001111100110000010100100111101111111 0
b00100111101101001011001001011001111100110000010100100111101111111 3
b00010011110110100101100100101100111110011000001010010011110111111 6
b001 <
1=
b101 J
#138
0=
#139
b0011011 #
b0000000000000000000000000000010001010001100000011100101011111101 $
b00011010101100111110010101110011101010111101111011000000000011111 -
b00110001001000101001000010100001101010011001001100010000000101110 0
b00110001001000101001000010100001101010011001001100010000000101110 3
b00011000100100010100100001010000110101001100100110001000000010111 6
19
b101 <
1=
b001 J
#140
0=
#141
b00011000100100010100100001010000110101001100100110001000000010111 *
b00110011010001010010110111000100100000001010100001001000000110110 0
b00110011010001010010110111000100100000001010100001001000000110110 3
b00011001101000101001011011100010010000000101010000100100000011011 6
b001 <
1=
b010 J
#142
0=
#143
b0011100 #
b0000000000000000000000000000001000101000110000001110010101111110 $
b00010001010001100000011100101011111101010101000011010111101110000 -
b00101001110101110100111101111100110010100001101001011111110000111 0
b00101001110101110100111101111100110010100001101001011111110000111 3
b00101001110101110100111101111100110010100001101001011111110000111 6
09
1;
b010 <
1=
b011 J
#144
0=
#145
b00101001110101110100111101111100110010100001101001011111110000111 *
b00011010101100111110010101110011101010111101111011000000000011111 -
b01000100100010110011010011110000011101011111100100011111110100110 0
b01000100100010110011010011110000011101011111100100011111110100110 3
b00100010010001011001101001111000001110101111110010001111111010011 6
19
0;
b011 <
1=
b001 J
#146
0=
#147
b00100010010001011001101001111000001110101111110010001111111010011 *
b00111100111110010111111111101011111001101101101101001111111110010 0
b00111100111110010111111111101011111001101101101101001111111110010 3
b00011110011111001011111111110101111100110110110110100111111111001 6
b001 <
1=
b101 J
#148
0=
#149
b0011101 #
b0000000000000000000000000000000100010100011000000111001010111111 $
b101 <
1=
b001 J
#150
0=
#151
b00011110011111001011111111110101111100110110110110100111111111001 *
b00111001001100001010010101101001100111110100110001101000000011000 0
b00111001001100001010010101101001100111110100110001101000000011000 3
b00011100100110000101001010110100110011111010011000110100000001100 6
b001 <
1=
b010 J
#152
0=
#153
b0011110 #
b0000000000000000000000000000000010001010001100000011100101011111 $
b00010001010001100000011100101011111101010101000011010111101110000 -
b00101111110000101100011100100001111010001011111001111111101101001 0
b00101111110000101100011100100001111010001011111001111111101101001 3
b00101111110000101100011100100001111010001011111001111111101101001 6
09
1;
b010 <
1=
b011 J
#154
0=
#155
b00101111110000101100011100100001111010001011111001111111101101001 *
b00011010101100111110010101110011101010111101111011000000000011111 -
b01001010011101101010110010010101100101001001110100111111110001000 0
b01001010011101101010110010010101100101001001110100111111110001000 3
b00100101001110110101011001001010110010100100111010011111111000100 6
19
0;
b011 <
1=
b001 J
#156
0=
#157
b00100101001110110101011001001010110010100100111010011111111000100 *
b00111111111011110011101110111110011101100010110101011111111100011 0
b00111111111011110011101110111110011101100010110101011111111100011 3
b00011111111101111001110111011111001110110001011010101111111110001 6
b001 <
1=
b100 J
#158
0=
#159
b0011111 #
b0000000000000000000000000000000001000101000110000001110010101111 $
b00010001010001100000011100101011111101010101000011010111101110000 -
b00110110100000010101110101110110101111111001111101110111100110100 0
b00110110100000010101110101110110101111111001111101110111100110100 3
b00011011010000001010111010111011010111111100111110111011110011010 6
09
b100 <
1=
b001 J
#160
0=
#161
b00011011010000001010111010111011010111111100111110111011110011010 *
b00101100100001101011010111100111010101010010000010010011100001010 0
b00101100100001101011010111100111010101010010000010010011100001010 3
b00010110010000110101101011110011101010101001000001001001110000101 6
b001 <
1=
b100 J
#162
0=
#163
b0100000 #
b0000000000000000000000000000000000100010100011000000111001010111 $
b100 <
1=
b001 J
#164
0=
#165
b00010110010000110101101011110011101010101001000001001001110000101 *
b00100111100010010110001000011111100111111110000100100001011110101 0
b00100111100010010110001000011111100111111110000100100001011110101 3
b00010011110001001011000100001111110011111111000010010000101111010 6
b001 <
1=
b010 J
#166
0=
#167
b0100001 #
b0000000000000000000000000000000000010001010001100000011100101011 $
b00100111100010010110001000011111100111111110000100100001011110101 6
1;
b010 <
1=
b011 J
#168
0=
#169
b00100111100010010110001000011111100111111110000100100001011110101 *
b00011010101100111110010101110011101010111101111011000000000011111 -
b01000010001111010100011110010011010010111011111111100001100010100 0
b01000010001111010100011110010011010010111011111111100001100010100 3
b00100001000111101010001111001001101001011101111111110000110001010 6
19
0;
b011 <
1=
b001 J
#170
0=
#171
b00100001000111101010001111001001101001011101111111110000110001010 *
b00111011110100101000100100111101010100011011111010110000110101001 0
b00111011110100101000100100111101010100011011111010110000110101001 3
b00011101111010010100010010011110101010001101111101011000011010100 6
b001 <
1=
b100 J
#172
0=
#173
b0100010 #
b0000000000000000000000000000000000001000101000110000001110010101 $
b00010001010001100000011100101011111101010101000011010111101110000 -
b00110010011001001010101011110101100110110011000011001000011111010 0
b00110010011001001010101011110101100110110011000011001000011111010 3
b00011001001100100101010101111010110011011001100001100100001111101 6
09
b100 <
1=
b001 J
#174
0=
#175
b00011001001100100101010101111010110011011001100001100100001111101 *
b00101010011110000101110010100110110000101110100100111011111101101 0
b00101010011110000101110010100110110000101110100100111011111101101 3
b00010101001111000010111001010011011000010111010010011101111110110 6
b001 <
1=
b010 J
#176
0=
#177
b0100011 #
b0000000000000000000000000000000000000100010100011000000111001010 $
b00101010011110000101110010100110110000101110100100111011111101101 6
1;
b010 <
1=
b011 J
#178
0=
#179
b00101010011110000101110010100110110000101110100100111011111101101 *
b00011010101100111110010101110011101010111101111011000000000011111 -
b01000101001011000100001000011010011011101100011111111100000001100 0
b01000101001011000100001000011010011011101100011111111100000001100 3
b00100010100101100010000100001101001101110110001111111110000000110 6
19
0;
b011 <
1=
b001 J
#180
0=
#181
b00100010100101100010000100001101001101110110001111111110000000110 *
b00111101010010100000011010000000111000110100001010111110000100101 0
b00111101010010100000011010000000111000110100001010111110000100101 3
b00011110101001010000001101000000011100011010000101011111000010010 6
b001 <
1=
b110 J
#182
0=
#183
b0100100 #
b0000000000000000000000000000000000000010001010001100000011100101 $
b00100010100101100010000100001101001101110110001111111110000000110 3
b00010001010010110001000010000110100110111011000111111111000000011 6
1:
b110 <
1=
b001 J
#184
0=
#185
b00010001010010110001000010000110100110111011000111111111000000011 *
b00101011111111101111010111111010010001111001000010111111000100010 0
b00010001010010110001000010000110100110111011000111111111000000011 3
b00001000101001011000100001000011010011011101100011111111100000001 6
b001 <
1=
b010 J
#186
0=
#187
b0100101 #
b0000000000000000000000000000000000000001000101000110000001110010 $
b00010001010001100000011100101011111101010101000011010111101110000 -
b00100010100100010001011110110010100100010000001011010110101110011 0
b00100010100100010001011110110010100100010000001011010110101110011 3
b00100010100100010001011110110010100100010000001011010110101110011 6
09
0:
1;
b010 <
1=
b011 J
#188
0=
#189
b00100010100100010001011110110010100100010000001011010110101110011 *
b00011010101100111110010101110011101010111101111011000000000011111 -
b00111101010001001111110100100110001111001110000110010110110010010 0
b00111101010001001111110100100110001111001110000110010110110010010 3
b00011110101000100111111010010011000111100111000011001011011001001 6
19
0;
b011 <
1=
b001 J
#190
0=
#191
b00011110101000100111111010010011000111100111000011001011011001001 *
b00111001010101100110010000000110110010100100111110001011011101000 0
b00111001010101100110010000000110110010100100111110001011011101000 3
b00011100101010110011001000000011011001010010011111000101101110100 6
b001 <
1=
b101 J
#192
0=
#193
b0100110 #
b0000000000000000000000000000000000000000100010100011000000111001 $
b101 <
1=
b001 J
#194
0=
#195
b00011100101010110011001000000011011001010010011111000101101110100 *
b00110111010111110001011101110111000100010000011010000101110010011 0
b00110111010111110001011101110111000100010000011010000101110010011 3
b00011011101011111000101110111011100010001000001101000010111001001 6
b001 <
1=
b100 J
#196
0=
#197
b0100111 #
b0000000000000000000000000000000000000000010001010001100000011100 $
b00010001010001100000011100101011111101010101000011010111101110000 -
b00101101111100010011100100101111010110100111100010011101011100100 0
b00101101111100010011100100101111010110100111100010011101011100100 3
b00010110111110001001110010010111101011010011110001001110101110010 6
09
b100 <
1=
b001 J
#198
0=
#199
b00010110111110001001110010010111101011010011110001001110101110010 *
b00101000001111101010001111000011101000101000110100100110011100010 0
b00101000001111101010001111000011101000101000110100100110011100010 3
b00010100000111110101000111100001110100010100011010010011001110001 6
b001 <
1=
b110 J
#200
0=
#201
b0101000 #
b0000000000000000000000000000000000000000001000101000110000001110 $
b00011010101100111110010101110011101010111101111011000000000011111 -
b00110001101011001000001000001011010110010001101100001110110010001 0
b00010110111110001001110010010111101011010011110001001110101110010 3
b00001011011111000100111001001011110101101001111000100111010111001 6
19
1:
b110 <
1=
b001 J
#202
0=
#203
b00001011011111000100111001001011110101101001111000100111010111001 *
b00100110001100000011001110111111100000100111110011100111011011000 0
b00001011011111000100111001001011110101101001111000100111010111001 3
b00000101101111100010011100100101111010110100111100010011101011100 6
b001 <
1=
b101 J
#204
0=
